LICENSE
MANIFEST.in
Makefile
README.rst
setup.py
tox.ini
docs/Makefile
docs/__init__.py
docs/changelog.rst
docs/conf.py
docs/ctx_manager.rst
docs/index.rst
docs/make.bat
docs/testing.rst
docs/utils.rst
docs/_build/.buildinfo
docs/_build/changelog.html
docs/_build/ctx_manager.html
docs/_build/ctx_manger.html
docs/_build/genindex.html
docs/_build/index.html
docs/_build/objects.inv
docs/_build/py-modindex.html
docs/_build/search.html
docs/_build/searchindex.js
docs/_build/testing.html
docs/_build/utils.html
docs/_build/.doctrees/changelog.doctree
docs/_build/.doctrees/ctx_manager.doctree
docs/_build/.doctrees/ctx_manger.doctree
docs/_build/.doctrees/environment.pickle
docs/_build/.doctrees/index.doctree
docs/_build/.doctrees/testing.doctree
docs/_build/.doctrees/utils.doctree
docs/_build/_modules/index.html
docs/_build/_modules/openS3/ctx_manager.html
docs/_build/_modules/openS3/utils.html
docs/_build/_sources/changelog.txt
docs/_build/_sources/ctx_manager.txt
docs/_build/_sources/ctx_manger.txt
docs/_build/_sources/index.txt
docs/_build/_sources/testing.txt
docs/_build/_sources/utils.txt
docs/_build/_static/ajax-loader.gif
docs/_build/_static/basic.css
docs/_build/_static/comment-bright.png
docs/_build/_static/comment-close.png
docs/_build/_static/comment.png
docs/_build/_static/default.css
docs/_build/_static/doctools.js
docs/_build/_static/down-pressed.png
docs/_build/_static/down.png
docs/_build/_static/file.png
docs/_build/_static/jquery.js
docs/_build/_static/minus.png
docs/_build/_static/plus.png
docs/_build/_static/pygments.css
docs/_build/_static/searchtools.js
docs/_build/_static/sidebar.js
docs/_build/_static/underscore.js
docs/_build/_static/up-pressed.png
docs/_build/_static/up.png
docs/_build/_static/websupport.js
docs/_build/doctrees/environment.pickle
docs/_build/doctrees/index.doctree
docs/_build/html/.buildinfo
docs/_build/html/genindex.html
docs/_build/html/index.html
docs/_build/html/objects.inv
docs/_build/html/search.html
openS3.egg-info/PKG-INFO
openS3.egg-info/SOURCES.txt
openS3.egg-info/dependency_links.txt
openS3.egg-info/top_level.txt
