Metadata-Version: 1.1
Name: openS3
Version: 0.2.0
Summary: A pythonic way to upload and download from AWS S3.
Home-page: http://github.com/logston/openS3
Author: Paul Logston
Author-email: code@logston.me
License: Copyright (c) 2014, Paul Logston
